sociaml/__init__.py
sociaml/analysis.py
sociaml/audio_analysis.py
sociaml/datastructures.py
sociaml/preprocessing.py
sociaml/text_analysis.py
sociaml/utils.py
sociaml/video_analysis.py
sociaml/models/__init__.py
sociaml/models/wav2vec2LargeRobust12ftEmotionMspDim.py
sociaml-0.1.4.dist-info/METADATA
sociaml-0.1.4.dist-info/WHEEL
sociaml-0.1.4.dist-info/licenses/LICENSE.md
sociaml-0.1.4.dist-info/RECORD
