Metadata-Version: 2.3
Name: sociaML
Version: 0.1.4
Summary: sociaML - the Swiss Army knife for audiovisual and textual video feature extraction.
Author-email: David Zollikofer <david@zollikofer.co>
License: MIT
License-File: LICENSE.md
Requires-Python: <3.13,>=3.10
Requires-Dist: dataclasses-json>=0.6.7
Requires-Dist: librosa>=0.10.2.post1
Requires-Dist: moviepy>=1.0.3
Requires-Dist: nltk>=3.9.1
Requires-Dist: numpy>=2.0.2
Requires-Dist: onnxruntime>=1.20.0
Requires-Dist: openai-whisper>=20240930
Requires-Dist: pandas>=2.2.3
Requires-Dist: pip>=24.3.1
Requires-Dist: presidio-analyzer>=2.2.355
Requires-Dist: presidio-anonymizer>=2.2.355
Requires-Dist: py-feat>=0.6.1
Requires-Dist: pyannote-audio>=3.3.2
Requires-Dist: sentence-transformers>=3.2.1
Requires-Dist: spacy>=3.8.2
Requires-Dist: tiktoken>=0.8.0
Requires-Dist: torchvision>=0.20.1
Requires-Dist: tqdm>=4.66.6
Requires-Dist: webvtt-py>=0.5.1
